mausy5043_common/__init__.py
mausy5043_common/funfile.py
mausy5043_common/funhomewizard.py
mausy5043_common/funmeteo.py
mausy5043_common/funsessy.py
mausy5043_common/funzeroconf.py
mausy5043_common/libsqlite3.py
mausy5043_common/py.typed
mausy5043_common/pyproject.toml
mausy5043_common-2.6.1.dist-info/METADATA
mausy5043_common-2.6.1.dist-info/WHEEL
mausy5043_common-2.6.1.dist-info/licenses/LICENSE
mausy5043_common-2.6.1.dist-info/RECORD
