Metadata-Version: 2.4
Name: mausy5043-common
Version: 2.6.1
Summary: Common python functions
Project-URL: Homepage, https://github.com/Mausy5043/mausy5043-common
Project-URL: Bug Tracker, https://github.com/Mausy5043/mausy5043-common/issues
Author: Mausy5043
License-Expression: MIT
License-File: LICENSE
Keywords: Debian Linux,Raspberry Pi,private
Classifier: Development Status :: 5 - Production/Stable
Classifier: License :: OSI Approved :: MIT License
Classifier: Operating System :: OS Independent
Classifier: Programming Language :: Python :: 3.12
Classifier: Programming Language :: Python :: 3.13
Requires-Python: >=3.12
Requires-Dist: numpy
Requires-Dist: pandas
Requires-Dist: pyarrow
Requires-Dist: python-homewizard-energy==9.3.0
Requires-Dist: sessypy==0.2.2
Requires-Dist: zeroconf~=0.147
